example/app.py
quickrest/__init__.py
quickrest/router_factory.py
quickrest/mixins/__init__.py
quickrest/mixins/access_control.py
quickrest/mixins/base.py
quickrest/mixins/create.py
quickrest/mixins/delete.py
quickrest/mixins/errors.py
quickrest/mixins/patch.py
quickrest/mixins/read.py
quickrest/mixins/resource.py
quickrest/mixins/search.py
quickrest/mixins/utils.py
tests/conftest.py
tests/test_create.py
tests/test_delete.py
tests/test_env_resource.py
tests/test_patch.py
tests/test_primary_key.py
tests/test_read.py
tests/test_search.py
fastapi_quickrest-0.0.0.dist-info/LICENSE
fastapi_quickrest-0.0.0.dist-info/METADATA
fastapi_quickrest-0.0.0.dist-info/WHEEL
fastapi_quickrest-0.0.0.dist-info/top_level.txt
fastapi_quickrest-0.0.0.dist-info/RECORD
