Metadata-Version: 2.1
Name: fastapi-quickrest
Version: 0.0.0
Summary: You deserve a...
Author-email: Lucas Kruitwagen <lucas.kruitwagen@gmail.com>
Project-URL: Source, https://github.com/lkruitwagen/quickrest
Classifier: Development Status :: 3 - Alpha
Classifier: Intended Audience :: Science/Research
Classifier: Topic :: Scientific/Engineering
Classifier: Programming Language :: Python :: 3 :: Only
Requires-Python: >=3.12
License-File: LICENSE
Requires-Dist: fastapi
Requires-Dist: pydantic-settings
Requires-Dist: sqlalchemy
Requires-Dist: uvicorn
Provides-Extra: dev
Requires-Dist: pytest; extra == "dev"
Requires-Dist: pytest-cov; extra == "dev"
Requires-Dist: pre-commit; extra == "dev"
Requires-Dist: pytest-ordering; extra == "dev"
Requires-Dist: mkdocs-material; extra == "dev"
Requires-Dist: mkdocstrings-python; extra == "dev"
Requires-Dist: httpx; extra == "dev"
Requires-Dist: mypy; extra == "dev"
